ec2_demo/__init__.py
ec2_demo/cli.py
ec2_demo/instances.py
tests/__init__.py
tests/test_instances.py
ec2_demo-0.1.9.dist-info/METADATA
ec2_demo-0.1.9.dist-info/WHEEL
ec2_demo-0.1.9.dist-info/entry_points.txt
ec2_demo-0.1.9.dist-info/top_level.txt
ec2_demo-0.1.9.dist-info/RECORD
