Metadata-Version: 2.1
Name: ec2-demo
Version: 0.1.9
Summary: EC2 demo
Home-page: https://github.com/jpedro/ec2-demo
Download-URL: https://github.com/jpedro/ec2-demo/tarball/master
Author: jpedro
Author-email: jpedro.barbosa@gmail.com
License: MIT
Keywords: ec2 create delete demo
Classifier: Development Status :: 3 - Alpha
Classifier: Intended Audience :: Developers
Classifier: Topic :: Software Development :: Build Tools
Classifier: License :: OSI Approved :: MIT License
Classifier: Programming Language :: Python :: 3
Requires-Python: >=3
Requires-Dist: pyyaml
Requires-Dist: jinja2
Requires-Dist: requests
Requires-Dist: boto3
Requires-Dist: tabulate
